example/__init__.py
example/notegod_test.py
notegod/__init__.py
notegod/changes/BChanges.py
notegod/changes/DrawGossip.py
notegod/changes/__init__.py
notegod/conf/GuaCi.py
notegod/conf/__init__.py
notegod/data/__init__.py
notegod/data/gua_ci/__init__.py
notegod/data/gua_ci/gwill_solution.py
notegod-0.0.2.dist-info/METADATA
notegod-0.0.2.dist-info/WHEEL
notegod-0.0.2.dist-info/top_level.txt
notegod-0.0.2.dist-info/RECORD
